tracely/__init__.py
tracely/_context.py
tracely/_env.py
tracely/_runtime_context.py
tracely/_tracer_provider.py
tracely/_version.py
tracely/context.py
tracely/decorators.py
tracely/evidently_cloud_client.py
tracely/interceptors.py
tracely/proxy.py
tracely-0.2.10.dist-info/METADATA
tracely-0.2.10.dist-info/WHEEL
tracely-0.2.10.dist-info/licenses/LICENSE
tracely-0.2.10.dist-info/RECORD
