Metadata-Version: 2.4
Name: tracely
Version: 0.2.10
Summary: Tracing tools
License: Apache-2.0
License-File: LICENSE
Author: Emeli Dral
Author-email: emeli.dral@gmail.com
Requires-Python: >=3.9,<4.0
Classifier: License :: OSI Approved :: Apache Software License
Classifier: Programming Language :: Python :: 3
Classifier: Programming Language :: Python :: 3.9
Classifier: Programming Language :: Python :: 3.10
Classifier: Programming Language :: Python :: 3.11
Classifier: Programming Language :: Python :: 3.12
Classifier: Programming Language :: Python :: 3.13
Classifier: Programming Language :: Python :: 3.14
Requires-Dist: opentelemetry-api (>=1.25.0)
Requires-Dist: opentelemetry-exporter-otlp-proto-grpc (>=1.25.0)
Requires-Dist: opentelemetry-exporter-otlp-proto-http (>=1.25.0)
Requires-Dist: opentelemetry-proto (>=1.25.0)
Requires-Dist: opentelemetry-sdk (>=1.25.0)
Requires-Dist: requests (>=2.32.0)
